dbt/__init__.py
dbt/adapters/extendedspark/__version__.py
dbt/adapters/setu/__init__.py
dbt/adapters/setu/client.py
dbt/adapters/setu/constants.py
dbt/adapters/setu/imports.py
dbt/adapters/setu/models.py
dbt/adapters/setu/python_platform_code.py
dbt/adapters/setu/session.py
dbt/adapters/setu/session_cursor.py
dbt/adapters/setu/session_handler.py
dbt/adapters/setu/session_manager.py
dbt/adapters/setu/setu_indbt_utils.py
dbt/adapters/setu/setu_python_submissions.py
dbt/adapters/setu/setu_session_request.py
dbt/adapters/setu/utils.py
dbt/adapters/spark/__init__.py
dbt/adapters/spark/__version__.py
dbt/adapters/spark/column.py
dbt/adapters/spark/connections.py
dbt/adapters/spark/impl.py
dbt/adapters/spark/li_connections.py
dbt/adapters/spark/li_impl.py
dbt/adapters/spark/li_python_submissions.py
dbt/adapters/spark/li_relation.py
dbt/adapters/spark/li_spark_utils.py
dbt/adapters/spark/python_submissions.py
dbt/adapters/spark/relation.py
dbt/adapters/spark/session.py
dbt/include/spark/__init__.py
dbt/include/spark/dbt_project.yml
dbt/include/spark/profile_template.yml
dbt/include/spark/macros/adapters.sql
dbt/include/spark/macros/apply_grants.sql
dbt/include/spark/macros/li_apply_retention.sql
dbt/include/spark/macros/li_catalog.sql
dbt/include/spark/macros/li_python.sql
dbt/include/spark/macros/materializations/clone.sql
dbt/include/spark/macros/materializations/indbt_python_prelude.sql
dbt/include/spark/macros/materializations/li_seeds.sql
dbt/include/spark/macros/materializations/li_snapshot.sql
dbt/include/spark/macros/materializations/li_table.sql
dbt/include/spark/macros/materializations/li_view.sql
dbt/include/spark/macros/materializations/seed.sql
dbt/include/spark/macros/materializations/snapshot.sql
dbt/include/spark/macros/materializations/table.sql
dbt/include/spark/macros/materializations/view.sql
dbt/include/spark/macros/materializations/incremental/column_helpers.sql
dbt/include/spark/macros/materializations/incremental/incremental.sql
in_dbt_spark-1.9.42.dist-info/METADATA
in_dbt_spark-1.9.42.dist-info/WHEEL
in_dbt_spark-1.9.42.dist-info/licenses/LICENSE
in_dbt_spark-1.9.42.dist-info/RECORD
