Metadata-Version: 2.4
Name: in-dbt-spark
Version: 1.9.42
Summary: Release for LinkedIn's changes to dbt-spark.
Project-URL: Homepage, https://github.com/dbt-labs/dbt-adapters/tree/main/dbt-spark
Project-URL: Documentation, https://docs.getdbt.com
Project-URL: Repository, https://github.com/linkedin-managed/in-dbt-adapters#subdirectory=dbt-spark
Project-URL: Issues, https://github.com/linkedin-managed/in-dbt-adapters
Project-URL: Changelog, https://github.com/linkedin-managed/in-dbt-adapters/blob/main/dbt-spark/CHANGELOG.md
Author-email: LinkedIn DBT Team <dbt-eng@linkedin.com>
Maintainer-email: LinkedIn DBT Team <dbt-eng@linkedin.com>
License-File: LICENSE
Keywords: LinkedIn,adapter,adapters,database,dbt Core,dbt Labs,dbt-core,elt,in-dbt,spark
Classifier: Development Status :: 5 - Production/Stable
Classifier: License :: OSI Approved :: Apache Software License
Classifier: Operating System :: MacOS :: MacOS X
Classifier: Operating System :: Microsoft :: Windows
Classifier: Operating System :: POSIX :: Linux
Classifier: Programming Language :: Python :: 3.9
Classifier: Programming Language :: Python :: 3.10
Classifier: Programming Language :: Python :: 3.11
Classifier: Programming Language :: Python :: 3.12
Requires-Python: >=3.9.0
Requires-Dist: dbt-adapters<2.0,>=1.7
Requires-Dist: dbt-common<2.0,>=1.10
Requires-Dist: dbt-core>=1.8.0
Requires-Dist: sqlparams>=3.0.0
Provides-Extra: all
Requires-Dist: pyhive[hive-pure-sasl]~=0.7.0; extra == 'all'
Requires-Dist: pyodbc~=5.1.0; extra == 'all'
Requires-Dist: pyspark<4.0.0,>=3.0.0; extra == 'all'
Requires-Dist: thrift<0.17.0,>=0.11.0; extra == 'all'
Provides-Extra: odbc
Requires-Dist: pyodbc~=5.1.0; extra == 'odbc'
Provides-Extra: pyhive
Requires-Dist: pyhive[hive-pure-sasl]~=0.7.0; extra == 'pyhive'
Requires-Dist: thrift<0.17.0,>=0.11.0; extra == 'pyhive'
Provides-Extra: session
Requires-Dist: pyspark<4.0.0,>=3.0.0; extra == 'session'
Provides-Extra: test
Requires-Dist: mock; extra == 'test'
Requires-Dist: pytest; extra == 'test'
Requires-Dist: pytest-dotenv; extra == 'test'
Requires-Dist: pytest-xdist; extra == 'test'
